allz/__init__.py
allz/defs.py
allz/cli/__init__.py
allz/cli/cmd.py
allz/decompress/__init__.py
allz/decompress/bz2_split_process.py
allz/decompress/decompress_main.py
allz/decompress/gz_split_process.py
allz/decompress/rar_process.py
allz/decompress/rar_split_process.py
allz/decompress/tar_7z_split_process.py
allz/decompress/tar_bz_process.py
allz/decompress/tar_split_process.py
allz/decompress/unar_process.py
allz/decompress/z7_split_process.py
allz/decompress/zip_process.py
allz/libs/__init__.py
allz/libs/abstract_decompress.py
allz/libs/common.py
allz/libs/file_type_tester.py
test/__init__.py
test/test_decompress.py
allz-0.1.4.dist-info/LICENSE
allz-0.1.4.dist-info/METADATA
allz-0.1.4.dist-info/WHEEL
allz-0.1.4.dist-info/entry_points.txt
allz-0.1.4.dist-info/top_level.txt
allz-0.1.4.dist-info/RECORD
